{
  "vacancy_id": "vac_701",
  "title": "UX/UI Designer (Figma)",
  "track": "data_analytics",
  "seniority": "Middle",
  "min_years_experience": 3,
  "company": "DemoCompany",
  "work_format": "Удаленно",
  "employment_type": "Полная",
  "domain": "product_design",
  "required_skills": [
    "Figma",
    "UX Design",
    "UI Design",
    "Wireframing",
    "Prototyping"
  ],
  "optional_skills": [
    "User Research",
    "Usability Testing",
    "Design System",
    "Accessibility"
  ],
  "tasks": [
    "Проектирование пользовательских сценариев и интерфейсов",
    "Работа с ключевыми инструментами: Figma, UX Design, UI Design, Wireframing",
    "Проектирование UX-flow, прототипирование, дизайн UI в Figma. Плюсом исследования и участие в дизайн-системе.",
    "Взаимодействие с командой направления Product Design"
  ],
  "raw_text": "Вакансия: UX/UI Designer (Figma)\nКомпания: DemoCompany\nФормат работы: Удаленно\nЗанятость: Полная\nОпыт работы: от 3 лет\nДомен: product_design\n\nВаши задачи:\n— Проектирование пользовательских сценариев и интерфейсов\n— Работа с ключевыми инструментами: Figma, UX Design, UI Design, Wireframing\n— Проектирование UX-flow, прототипирование, дизайн UI в Figma. Плюсом исследования и участие в дизайн-системе.\n— Взаимодействие с командой направления Product Design\n\nНаши ожидания:\n— Figma\n— UX Design\n— UI Design\n— Wireframing\n— Prototyping\n\nБудет плюсом:\n— User Research\n— Usability Testing\n— Design System\n— Accessibility"
}